instaui_shiki/__init__.py
instaui_shiki/_decorations.py
instaui_shiki/_shiki_code.py
instaui_shiki/consts.py
instaui_shiki/resources.py
instaui_shiki/types.py
instaui_shiki/version.py
instaui_shiki/zero_ext_resolver.py
instaui_shiki/cdn/__init__.py
instaui_shiki/cdn/_cdn.py
instaui_shiki/static/shiki-code-logic.js
instaui_shiki/static/shiki-code.js
instaui_shiki/static/shiki-engine.js
instaui_shiki/static/shiki-style.css
instaui_shiki/static/shiki-transformers.js
instaui_shiki/static/langs/css.mjs
instaui_shiki/static/langs/markdown.mjs
instaui_shiki/static/langs/python.mjs
instaui_shiki/static/langs/shell.mjs
instaui_shiki/static/langs/shellscript.mjs
instaui_shiki/static/themes/vitesse-dark.mjs
instaui_shiki/static/themes/vitesse-light.mjs
instaui_shiki-0.6.4.dist-info/METADATA
instaui_shiki-0.6.4.dist-info/WHEEL
instaui_shiki-0.6.4.dist-info/licenses/LICENSE
instaui_shiki-0.6.4.dist-info/RECORD
