Metadata-Version: 2.4
Name: instaui-shiki
Version: 0.6.4
Summary: A Python package for instaui-shiki.
Author-email: CrystalWindSnake <568166495@qq.com>
License-Expression: MIT
License-File: LICENSE
Keywords: gui,shiki,syntax-highlighting,ui,web
Requires-Python: <3.14,>=3.10
Requires-Dist: instaui>=0.8.7
